<?xml version="1.0" encoding="UTF-8"?>
<script>
  <metadata>
    <priority>0</priority>
    <owner>squintal</owner>
    <runcontext>caller</runcontext>
  </metadata>
  <parameter name="t" type="interval" trigger="true" relative="false" value="" offset="00:00:00" interval="01:00:00"/>
  <code><![CDATA[// Energia Importada
var Energia_Importada = Ua.findNode(base + ".Energia_Importada");
var Energia_Importada_Historico = Ua.findNode(base + ".Energia_Importada_Historico");
Energia_Importada_Historico.result.value = Energia_Importada.result.value;]]></code>
</script>
